dkrs/__init__.py
dkrs/unicode.py
dkrs/color/__init__.py
dkrs/file/__init__.py
dkrs/git/__init__.py
dkrs/log/__init__.py
dkrs/request/__init__.py
dkrs/system/__init__.py
dkrs/time/__init__.py
dkrs-0.1.4.dist-info/LICENSE
dkrs-0.1.4.dist-info/METADATA
dkrs-0.1.4.dist-info/WHEEL
dkrs-0.1.4.dist-info/top_level.txt
dkrs-0.1.4.dist-info/RECORD
